tracsubtickets/__init__.py
tracsubtickets/api.py
tracsubtickets/checker.py
tracsubtickets/db_default.py
tracsubtickets/web_ui.py
tracsubtickets/htdocs/css/subtickets.css
TracSubTickets-0.5.4.dist-info/METADATA
TracSubTickets-0.5.4.dist-info/WHEEL
TracSubTickets-0.5.4.dist-info/entry_points.txt
TracSubTickets-0.5.4.dist-info/top_level.txt
TracSubTickets-0.5.4.dist-info/RECORD
