Metadata-Version: 2.1
Name: TracSubTickets
Version: 0.5.4
Summary: Trac Sub-Tickets Plugin
Home-page: http://github.com/trac-hacks/trac-subtickets-plugin
Author: Takashi Ito
Author-email: TakashiC.Ito@gmail.com
Maintainer: Theodor Norup
Maintainer-email: theodor.norup@gmail.com
License: BSD
Keywords: trac plugin ticket subticket
Platform: UNKNOWN
